Metadata-Version: 2.1
Name: similar-sentences
Version: 1.6
Summary: Similar sentence prediction
Home-page: https://github.com/shangan23/similar-sentences
Author: Shankar Ganesh Jayaraman
Author-email: shangan.23@gmail.com
License: UNKNOWN
Platform: UNKNOWN
Classifier: Development Status :: 4 - Beta
Classifier: Programming Language :: Python :: 3
Classifier: License :: OSI Approved :: Apache Software License
Classifier: Operating System :: OS Independent
Requires-Python: >=3.6
